fancytest/__init__.py
fancytest/main.py
fancytest-1.1.dist-info/METADATA
fancytest-1.1.dist-info/WHEEL
fancytest-1.1.dist-info/top_level.txt
fancytest-1.1.dist-info/RECORD
