Metadata-Version: 2.1
Name: fancytest
Version: 1.1
Summary: Test function call instances using a simple decorator.
Author: Ian Jure Macalisang
Author-email: ianjuremacalisang2@gmail.com
Requires: termcolor
Requires: time
